{
    "toiletAddress":[{"index":1,"name":"경로공원","address":"(중촌동 382-1)","like":0,"hate":0},
    {"index":2,"name":"중촌근린공원","address":"(중촌동 260)","like":0,"hate":0},
    {"index":3,"name":"대흥어린이공원","address":"(대흥동 160)","like":0,"hate":0},
    {"index":4,"name":"테미근린공원","address":"(대흥동 326-54)","like":0,"hate":0},
    {"index":5,"name":"용머리어린이공원","address":"(용두동 162-1)","like":0,"hate":0},
    {"index":6,"name":"평리어린이공원","address":"(태평1동 266-3)","like":0,"hate":0},
    {"index":7,"name":"강변공원","address":"(태평2동 368)","like":0,"hate":0},
    {"index":8,"name":"버드내조폐근린공원","address":"(태평2동 510-162)","like":0,"hate":0},
    {"index":9,"name":"버드내어린이공원","address":"(유천1동 275-5)","like":0,"hate":0},
    {"index":10,"name":"중평어린이공원","address":"(유천1동 315-1)","like":0,"hate":0},
    {"index":11,"name":"서대전광장(음악당)","address":"(문화1동 1-39)","like":0,"hate":0},
    {"index":12,"name":"서대전광장(광장내)","address":"(문화1동 1-39)","like":0,"hate":0},
    {"index":13,"name":"옥미어린이공원","address":"(문화2동 484-8)","like":0,"hate":0},
    {"index":14,"name":"모산어린이공원","address":"(문화2동 563-3)","like":0,"hate":0},
    {"index":15,"name":"천근어린이공원","address":"(문화2동 458-14)","like":0,"hate":0},
    {"index":16,"name":"당대어린이공원","address":"(산성동 36-1)","like":0,"hate":0},
    {"index":17,"name":"멋티어린이공원","address":"(산성동 122-14)","like":0,"hate":0},
    {"index":18,"name":"원대어린이공원","address":"(산성동 118-7)","like":0,"hate":0},
    {"index":19,"name":"탑골어린이공원","address":"(산성동 299-28)","like":0,"hate":0},
    {"index":20,"name":"사정1어린이공원","address":"(사정동 360)","like":0,"hate":0},
    {"index":21,"name":"안영2어린이공원","address":"(안영동 664)","like":0,"hate":0},
    {"index":22,"name":"양지근린공원","address":"(선화동362-97)","like":0,"hate":0},
    {"index":23,"name":"은행동상점가 고객지원센터","address":"(중교로 83)","like":0,"hate":0},
    {"index":24,"name":"무수동농촌","address":"(운남로85번길 32-8)","like":0,"hate":0},
    {"index":25,"name":"은행동상점가 고객지원센터","address":"(대전천서로 439-13)","like":0,"hate":0},
    {"index":26,"name":"단재신채호선생생가지","address":"(어남동233)","like":0,"hate":0},
    {"index":27,"name":"중촌게이트볼장 옆 화장실","address":"(중촌고가도로 밑)","like":0,"hate":0},
    {"index":28,"name":"교통광장","address":"(침산동 360번지 )","like":0,"hate":0},
    {"index":29,"name":"중앙광장","address":"(침산동산34번지)","like":0,"hate":0},
    {"index":30,"name":"으뜸화장실","address":"(보문산공원로497번길14)","like":0,"hate":0},
    {"index":31,"name":"청소년문화마당","address":"(선화로 119번길 16-3)","like":0,"hate":0},
    {"index":32,"name":"서대전초교 뒤","address":"(용두로28번길22-6)","like":0,"hate":0},
    {"index":33,"name":"용정아파트밑","address":"(용두로28번길21-14)","like":0,"hate":0},
    {"index":34,"name":"동지회","address":"(중촌동 429-27)","like":0,"hate":0},
    {"index":35,"name":"목척시장","address":"(목척5길126)","like":0,"hate":0},
    {"index":36,"name":"서대전육교 밑","address":"(유천동187-7)","like":0,"hate":0},
    {"index":37,"name":"효문화마을","address":"(중구 뿌리공원로 47)","like":0,"hate":0},
    {"index":38,"name":"푸른어린이공원","address":"(선화동 162-1)","like":0,"hate":0}]
}